proxyprinter/__init__.py
proxyprinter/proxyprinter.css
proxyprinter/proxyprinter.py
proxyprinter-0.3.1.dist-info/LICENSE
proxyprinter-0.3.1.dist-info/METADATA
proxyprinter-0.3.1.dist-info/WHEEL
proxyprinter-0.3.1.dist-info/entry_points.txt
proxyprinter-0.3.1.dist-info/top_level.txt
proxyprinter-0.3.1.dist-info/RECORD
