Metadata-Version: 2.1
Name: proxyprinter
Version: 0.3.1
Summary: Generate card game mockups from .ods spreadsheets
Home-page: https://github.com/mduo13/proxyprinter
Author: Rome Reginelli
Author-email: mduo13@gmail.com
License: MIT
Keywords: games mockups proxying design
Platform: UNKNOWN
Classifier: Development Status :: 4 - Beta
Classifier: Environment :: Console
Classifier: Intended Audience :: End Users/Desktop
Classifier: License :: OSI Approved :: GNU General Public License v3 (GPLv3)
Classifier: Operating System :: POSIX
Classifier: Programming Language :: Python :: 3
Classifier: Programming Language :: Python :: 3.4
Classifier: Topic :: Utilities
Classifier: Topic :: Games/Entertainment :: Board Games
Requires-Dist: pyexcel-ods3
